ChebTools/ChebTools.cpython-310-x86_64-linux-gnu.so
ChebTools/py.typed
ChebTools/ChebTools.pyi
chebtools-1.13.0.dist-info/RECORD
chebtools-1.13.0.dist-info/WHEEL
chebtools-1.13.0.dist-info/METADATA
chebtools-1.13.0.dist-info/licenses/LICENSE
