Metadata-Version: 2.1
Name: chebtools
Version: 1.13.0
Summary: Tools for working with Chebyshev expansion
Author-Email: Ian Bell <ian.bell@nist.gov>
Project-URL: Homepage, https://github.com/usnistgov/teqpflsh
Requires-Python: >=3.8
